qphase_viz/__init__.py
qphase_viz/config.py
qphase_viz/engine.py
qphase_viz/plotters/base.py
qphase_viz/plotters/evolution.py
qphase_viz/plotters/phase.py
qphase_viz/plotters/spectrum.py
qphase_viz-1.0.0.dist-info/licenses/LICENSE
qphase_viz-1.0.0.dist-info/METADATA
qphase_viz-1.0.0.dist-info/WHEEL
qphase_viz-1.0.0.dist-info/entry_points.txt
qphase_viz-1.0.0.dist-info/top_level.txt
qphase_viz-1.0.0.dist-info/RECORD
