Metadata-Version: 2.4
Name: qphase-viz
Version: 1.0.0
Summary: Visualization plugin for QPhase: Phase Portraits and PSD Analysis
Project-URL: Homepage, https://github.com/PolarisMegrez/qphase
Project-URL: Repository, https://github.com/PolarisMegrez/qphase
Project-URL: Issues, https://github.com/PolarisMegrez/qphase/issues
Classifier: Programming Language :: Python :: 3
Classifier: Programming Language :: Python :: 3.10
Classifier: Programming Language :: Python :: 3.11
Classifier: Programming Language :: Python :: 3.12
Classifier: License :: OSI Approved :: MIT License
Classifier: Operating System :: OS Independent
Classifier: Intended Audience :: Science/Research
Classifier: Topic :: Scientific/Engineering :: Physics
Classifier: Topic :: Software Development :: Libraries
Requires-Python: >=3.10
License-File: LICENSE
Requires-Dist: matplotlib>=3.6
Requires-Dist: numpy>=1.23
Requires-Dist: scipy>=1.10
Requires-Dist: qphase>=1.0.0
Requires-Dist: qphase-sde>=1.0.0
Dynamic: license-file
